{
    "id": "nm17942099",
    "displayName": "Sadie McGraw",
    "primaryImage": {
        "url": "https://m.media-amazon.com/images/M/MV5BMzVjNjVlMDItMjJjMC00ZGNhLTgyMTQtOTJkZmFhNzY1ZGZiXkEyXkFqcGc@._V1_.jpg",
        "width": 1053,
        "height": 1580
    },
    "primaryProfessions": [
        "actress",
        "miscellaneous",
        "production_department"
    ],
    "biography": "Sadie McGraw is known for Avatar: Fire and Ash (2025), People We Meet on Vacation (2026) and Weapons (2025)."
}