{
    "triviaEntries": [
        {
            "id": "nt0321101",
            "text": "Named Best Modern Actress in an Entertainment Weekly online poll, substantially beating out runner-up Michelle Pfeiffer.",
            "interestCount": 62,
            "voteCount": 67
        },
        {
            "id": "nt0321102",
            "text": "Learned to play the violin, by practicing six hours a day for eight weeks, for her role in Music of the Heart (1999).",
            "interestCount": 324,
            "voteCount": 330
        },
        {
            "id": "nt0321103",
            "text": "Has a fear of helicopters.",
            "interestCount": 137,
            "voteCount": 144
        },
        {
            "id": "nt0321105",
            "text": "Listed as one of 12 \"Promising New Actors of 1977\" in John Willis' Screen World, Vol. 29.",
            "interestCount": 31,
            "voteCount": 39
        },
        {
            "id": "nt0321106",
            "text": "Ranked #24 in Empire (UK) magazine's \"The Top 100 Movie Stars of All Time\" list.",
            "interestCount": 24,
            "voteCount": 27
        },
        {
            "id": "nt0321107",
            "text": "Received her Master's degree in Fine Arts from Yale University in New Haven, Connecticut (1975).",
            "interestCount": 285,
            "voteCount": 292
        },
        {
            "id": "nt0321108",
            "text": "Received her Bachelor's degree cum laude from Vassar College in Poughkeepsie, New York (1971).",
            "interestCount": 51,
            "voteCount": 57
        },
        {
            "id": "nt0321109",
            "text": "Was romantically involved with actor John Cazale for two years, culminating with his death at age 42 in 1978 from lung cancer. She is very reluctant to discuss the relationship with anyone. The couple had been sharing a loft at 146 Franklin Street in Manhattan's Tribeca district.",
            "interestCount": 369,
            "voteCount": 377
        },
        {
            "id": "nt0321110",
            "text": "Attended and graduated from Bernards High School in Bernardsville, New Jersey (1967).",
            "interestCount": 20,
            "voteCount": 26
        },
        {
            "id": "nt0321111",
            "text": "Before succeeding as an actress, she was a waitress at the Hotel Somerset in Somerville, New Jersey.",
            "interestCount": 147,
            "voteCount": 155
        },
        {
            "id": "nt0321112",
            "text": "Was a cheerleader and homecoming queen in high school.",
            "interestCount": 288,
            "voteCount": 296
        },
        {
            "id": "nt0321113",
            "text": "She left her just-claimed Oscar for Kramer vs. Kramer (1979) on the back of a toilet during the 1979 festivities.",
            "interestCount": 529,
            "voteCount": 538
        },
        {
            "id": "nt0321114",
            "text": "Replaced Madonna for the lead role of Roberta Guaspari in Music of the Heart (1999).",
            "interestCount": 72,
            "voteCount": 78
        },
        {
            "id": "nt0321115",
            "text": "In 2001, her son, Henry W. Gummer (\"Hank\") was a student at Dartmouth College in New Hampshire.",
            "interestCount": 22,
            "voteCount": 32
        },
        {
            "id": "nt0321116",
            "text": "Sister-in-law of Maeve Kinkead.",
            "interestCount": 13,
            "voteCount": 26
        },
        {
            "id": "nt0321119",
            "text": "Tennessee Williams wanted her for a film version of \"A Streetcar Named Desire\" in the 1980s. When Streep proved unavailable, the project was refashioned for television and the role of Blanche given to Ann-Margret.",
            "interestCount": 38,
            "voteCount": 44
        },
        {
            "id": "nt0321121",
            "text": "Has a deviated septum, which she refuses to have fixed.",
            "interestCount": 150,
            "voteCount": 158
        },
        {
            "id": "nt0321124",
            "text": "The children's television series Sesame Street (1969) has featured a character named \"Meryl Sheep\" in her honor.",
            "interestCount": 201,
            "voteCount": 207
        },
        {
            "id": "nt0321125",
            "text": "Was originally supposed to play the role of Iris Hineman in Minority Report (2002), but had to back out. She was replaced by Lois Smith.",
            "interestCount": 28,
            "voteCount": 34
        },
        {
            "id": "nt0321126",
            "text": "Her character Karen Silkwood from her film Silkwood (1983) was ranked #47 on the American Film Institute Heroes list of the 100 years of the Greatest Screen Heroes and Villians.",
            "interestCount": 48,
            "voteCount": 52
        },
        {
            "id": "nt0321127",
            "text": "Presented Paul McCartney with the 1990 Grammy Lifetime Achievement award. Attended The Beatles concert at Shea Stadium in 1965 with an \"I love Paul\" sign, which she mentioned when presenting the award to McCartney.",
            "interestCount": 257,
            "voteCount": 266
        },
        {
            "id": "nt0321128",
            "text": "Older sister of Harry Streep and Dana Streep.",
            "interestCount": 19,
            "voteCount": 25
        },
        {
            "id": "nt0321129",
            "text": "Spent a year as a transfer student at Dartmouth College where she participated in theater.",
            "interestCount": 40,
            "voteCount": 47
        },
        {
            "id": "nt0321130",
            "text": "Originally applied to Law School but slept in on the morning of her interview and took it as a sign she was destined for other things.",
            "interestCount": 722,
            "voteCount": 734
        },
        {
            "id": "nt0321131",
            "text": "Sigourney Weaver and Christine Estabrook were fellow classmates at Yale Drama School.",
            "interestCount": 166,
            "voteCount": 174
        },
        {
            "id": "nt0321132",
            "text": "Back at Yale Drama School, she and Sigourney Weaver appeared in a play staged in a swimming pool together. The play was called \"The Frogs\".",
            "interestCount": 86,
            "voteCount": 91
        },
        {
            "id": "nt0321134",
            "text": "May 27, 2004 was proclaimed \"Meryl Streep Day\" by Manhattan Borough President C. Virginia Fields.",
            "interestCount": 106,
            "voteCount": 113
        },
        {
            "id": "nt0321135",
            "text": "She was voted the 37th Greatest Movie Star of all time by Entertainment Weekly.",
            "interestCount": 39,
            "voteCount": 42
        },
        {
            "id": "nt0321136",
            "text": "As a young actor, she performed at the Yale Repertory Theater with Christopher Lloyd.",
            "interestCount": 56,
            "voteCount": 60
        },
        {
            "id": "nt0321137",
            "text": "According to Katharine Hepburn's official biographer A. Scott Berg, Meryl Streep was her least favorite modern actress on screen: \"Click, click, click,\" she said, referring to the wheels turning inside Streep's head.",
            "interestCount": 70,
            "voteCount": 82
        },
        {
            "id": "nt0321138",
            "text": "Has only been turned down for six roles: Dwan in King Kong (1976), Ellen Ripley in Alien (1979), Michelle Straton in American Gigolo (1980), Patsy Cline in Sweet Dreams (1985), Miss Kenton in The Remains of the Day (1993), and Elizabeth I in Elizabeth (1998).",
            "interestCount": 252,
            "voteCount": 260
        },
        {
            "id": "nt0321141",
            "text": "Mentioned by first name only (with two-time co-star Jack Nicholson) in Michael Crichton's novel \"State of Fear\" (2004).",
            "interestCount": 20,
            "voteCount": 26
        },
        {
            "id": "nt0321142",
            "text": "Nominated for the 1976 Tony Award for Best Actress (Featured Role - Play) in Tennessee Williams' \"27 Wagons Full of Cotton\".",
            "interestCount": 13,
            "voteCount": 19
        },
        {
            "id": "nt0321143",
            "text": "Premiere magazine ranked her as #46 on a list of the Greatest Movie Stars of All Time in their Stars in Our Constellation feature (2005).",
            "interestCount": 14,
            "voteCount": 19
        },
        {
            "id": "nt0321145",
            "text": "Took serious singing lessons. At age 12, she studied to become an opera singer.",
            "interestCount": 169,
            "voteCount": 176
        },
        {
            "id": "nt0321146",
            "text": "Acting career began on the stage.",
            "interestCount": 39,
            "voteCount": 45
        },
        {
            "id": "nt0321147",
            "text": "Is the second of four consecutive winners of the Best Supporting Actress Oscar to have the initials \"M.S.\". The others are: Maggie Smith - California Suite (1978), Mary Steenburgen - Melvin and Howard (1980), and Maureen Stapleton - Reds (1981).",
            "interestCount": 33,
            "voteCount": 49
        },
        {
            "id": "nt0321148",
            "text": "Received her honorary degree (Doctor of Arts) from Middlebury College during her nephew's graduation (2004).",
            "interestCount": 20,
            "voteCount": 26
        },
        {
            "id": "nt0321149",
            "text": "She attended Harding Township Middle School in Harding, New Jersey for one or two years.",
            "interestCount": 12,
            "voteCount": 22
        },
        {
            "id": "nt0321150",
            "text": "Sold her New York City townhouse for $9.1 million in February 2006. She was forced to slash the asking price for the eight-bedroom Manhattan property from $12 million to secure a sale. Streep bought the house for $2.2 million in 1995, according to the New York Post.",
            "interestCount": 61,
            "voteCount": 67
        },
        {
            "id": "nt0321151",
            "text": "Early in her career, Streep received a letter from Bette Davis, whom most critics and cinema historians rank as the greatest American movie actress ever. Davis told Streep that she felt that she was her successor as the premier American actress. Davis, a double winner who was nominated 10 times for an Academy Award, all of them Best Actress nods, set the record for most acting nominations with her tenth in 1963 for What Ever Happened to Baby Jane? (1962), a record later surpassed by Katharine Hepburn with her 11th nomination (and 3rd win) for The Lion in Winter (1968). Hepburn extended her record with her 12th nomination (and fourth win) for On Golden Pond (1981).",
            "interestCount": 247,
            "voteCount": 254
        },
        {
            "id": "nt0321153",
            "text": "Her performance as Sophie Zawistowska in Sophie's Choice (1982) is ranked #3 on Premiere magazine's 100 Greatest Performances of All Time (2006).",
            "interestCount": 234,
            "voteCount": 240
        },
        {
            "id": "nt0321154",
            "text": "Her performance as Karen Silkwood in Silkwood (1983) is ranked #71 on Premiere magazine's 100 Greatest Performances of All Time (2006).",
            "interestCount": 33,
            "voteCount": 39
        },
        {
            "id": "nt0321155",
            "text": "Her husband, Don Gummer, is a sculptor.",
            "interestCount": 173,
            "voteCount": 179
        },
        {
            "id": "nt0321156",
            "text": "Her father was a drug company exec; her mother, an artist-turned-housewife who kept an art studio behind the house. Her father loved to play the piano and her mother to sing. Meryl was given singing lessons at a young age. Her mother died in 2001 and her father in 2004.",
            "interestCount": 74,
            "voteCount": 79
        },
        {
            "id": "nt0321157",
            "text": "Son Henry Gummer is an actor, filmmaker and co-founder of a rock band; daughter Mary Willa, whose stage name is Mamie Gummer, is an off-Broadway actress; daughter Grace Gummer is an actress; and daughter Louisa Jacobson is a model and actress.",
            "interestCount": 75,
            "voteCount": 80
        },
        {
            "id": "nt0321158",
            "text": "Friends with Jill Clayburgh. First met in their roles as mothers.",
            "interestCount": 22,
            "voteCount": 29
        },
        {
            "id": "nt0321160",
            "text": "The longest she has gone without an Oscar nomination is five years, between Postcards from the Edge (1990) and The Bridges of Madison County (1995).",
            "interestCount": 188,
            "voteCount": 195
        },
        {
            "id": "nt0321161",
            "text": "Robert De Niro said she is his favorite actress to work with.",
            "interestCount": 596,
            "voteCount": 609
        },
        {
            "id": "nt0321162",
            "text": "Was nominated for Best Actress in 1988 along with Cher. When Cher was announced, just before the cameras cut away from the other four actresses, Streep could be seen springing to her feet in delight and applauding for Cher. During her acceptance speech, Cher thanked Streep personally (addressing her as Mary Louise Streep), as they had worked together on Cher's first film, Silkwood (1983). As the camera briefly cut away to Streep sitting in the audience, she blew Cher a kiss.",
            "interestCount": 229,
            "voteCount": 239
        },
        {
            "id": "nt0321163",
            "text": "She was considered for the role of Evita Peron in Evita (1996), which went to Madonna.",
            "interestCount": 46,
            "voteCount": 53
        },
        {
            "id": "nt0321166",
            "text": "Donated her wardrobe from The Devil Wears Prada (2006) to a charity auction.",
            "interestCount": 281,
            "voteCount": 289
        },
        {
            "id": "nt0321168",
            "text": "Uses music, most often Classical, to get into character.",
            "interestCount": 193,
            "voteCount": 199
        },
        {
            "id": "nt0321169",
            "text": "Is a member of the Academy of Motion Picture Arts and Sciences (AMPAS).",
            "interestCount": 45,
            "voteCount": 50
        },
        {
            "id": "nt0321171",
            "text": "Nominated for a 2007 Drama Desk Award for her performance in \"Mother Courage and Her Children\" (Outstanding Actress in a Play).",
            "interestCount": 13,
            "voteCount": 20
        },
        {
            "id": "nt0321172",
            "text": "Daughter of Mary Streep and Harry Streep (a pharmaceutical executive).",
            "interestCount": 15,
            "voteCount": 24
        },
        {
            "id": "nt0321173",
            "text": "Her accumulation of 21 Oscar nominations (3 wins) was accomplished over a period of only 38 years. Bette Davis scored 10 nominations (2 wins) over 28 years (all leading roles). Katharine Hepburn garnered 12 nominations (4 wins) after a relatively lengthy 48 years (all leading roles).",
            "interestCount": 83,
            "voteCount": 90
        },
        {
            "id": "nt0321174",
            "text": "Occasionally mistaken for friend Glenn Close, Streep was pregnant with her fourth child while shopping in a Los Angeles baby store where the staff lavished her with huge amounts of baby paraphernalia. Just as she was about to leave they whispered, \"We loved you in Fatal Attraction (1987)\".",
            "interestCount": 323,
            "voteCount": 333
        },
        {
            "id": "nt0397740",
            "text": "She was inducted into the inaugural class of 2007 New Jersey Hall of Fame for her services to arts and entertainment. She inducted with the class of 2024.",
            "interestCount": 14,
            "voteCount": 18
        },
        {
            "id": "nt0398706",
            "text": "She and her daughter Mamie Gummer portrayed the same role at different ages in Evening (2007).",
            "interestCount": 94,
            "voteCount": 98
        },
        {
            "id": "nt0408327",
            "text": "Ranked #6 on Entertainment Weekly magazine's \"The 50 Smartest People in Hollywood (2007).",
            "interestCount": 102,
            "voteCount": 107
        },
        {
            "id": "nt0432958",
            "text": "Nominated for a 2008 Grammy Award for \"The One and Only Shrek\" (Best Spoken Word Album for Children).",
            "interestCount": 28,
            "voteCount": 34
        },
        {
            "id": "nt0477749",
            "text": "Has said she is a great fan of actor Leonardo DiCaprio.",
            "interestCount": 460,
            "voteCount": 476
        },
        {
            "id": "nt0523491",
            "text": "With the announcement of the 66th Annual Golden Globe Award nominations and receiving two nominations, the actress surpassed Jack Lemmon's count of 22 nominations and is now, besides holding the record for most Oscar nominations, the actor with the most Golden Globe nominations of all time with a total of 32 nominations.",
            "interestCount": 252,
            "voteCount": 257
        },
        {
            "id": "nt0550819",
            "text": "She was close friends with late actress Natasha Richardson.",
            "interestCount": 159,
            "voteCount": 165
        },
        {
            "id": "nt0553549",
            "text": "She attended Natasha Richardson's funeral along with husband Don Gummer.",
            "interestCount": 77,
            "voteCount": 86
        },
        {
            "id": "nt0562206",
            "text": "Signs cheques with her real name - Mary Louise Gummer.",
            "interestCount": 349,
            "voteCount": 358
        },
        {
            "id": "nt0566378",
            "text": "She was ranked #87 on Ellen DeGeneres' most sexy movie actors list (2009).",
            "interestCount": 38,
            "voteCount": 52
        },
        {
            "id": "nt0572437",
            "text": "Received her honorary degree from Princeton University in Princeton, New Jersey.",
            "interestCount": 37,
            "voteCount": 43
        },
        {
            "id": "nt0581935",
            "text": "She gained as much as 15 pounds while filming the Julie & Julia (2009) movie.",
            "interestCount": 114,
            "voteCount": 123
        },
        {
            "id": "nt0585634",
            "text": "Her fans call themselves \"Streepers\".",
            "interestCount": 210,
            "voteCount": 222
        },
        {
            "id": "nt0589789",
            "text": "In the stage show \"Fame\", though other actors are mentioned in song lyrics, she is the only actress to have her name in a song title. The song is called \"Think of Meryl Streep\" and takes place after Carmen kisses Nick when he asks her how she relaxes, and Serena (who wants Nick for herself) sees them.",
            "interestCount": 44,
            "voteCount": 49
        },
        {
            "id": "nt0610088",
            "text": "Studied acting with Michael Howard in New York City.",
            "interestCount": 11,
            "voteCount": 19
        },
        {
            "id": "nt0640618",
            "text": "Through the television series Faces of America with Henry Louis Gates Jr. (2010), she learned that she is a distant relative of director Mike Nichols.",
            "interestCount": 66,
            "voteCount": 70
        },
        {
            "id": "nt0642576",
            "text": "Resides in New York City and Salisbury, Connecticut.",
            "interestCount": 81,
            "voteCount": 85
        },
        {
            "id": "nt0643029",
            "text": "She presented the leadership award to ex-Colombian hostage Ingrid Betancourt.",
            "interestCount": 29,
            "voteCount": 33
        },
        {
            "id": "nt0682809",
            "text": "Landed the breakthrough role of Linda in The Deer Hunter (1978) after Robert De Niro had seen her playing Dunyasha in Anton Chekhov's \"The Cherry Orchard\" at Manhattan's Lincoln Center (1977). Streep had been playing opposite Irene Worth, Raul Julia and Mary Beth Hurt.",
            "interestCount": 72,
            "voteCount": 75
        },
        {
            "id": "nt0726912",
            "text": "On her 60th birthday, her husband brought her a toaster and one of her daughters brought her a rocking chair. Despite having to work until late on the day, her children cooked her a birthday meal when she returned.",
            "interestCount": 179,
            "voteCount": 194
        },
        {
            "id": "nt0726914",
            "text": "Attended Emily Blunt's and John Krasinski's wedding with her husband, Don Gummer.",
            "interestCount": 232,
            "voteCount": 252
        },
        {
            "id": "nt0727719",
            "text": "Kept the sunglasses she wore in The Devil Wears Prada (2006) and used them again during the \"Money Money Money\" sequence in Mamma Mia! (2008).",
            "interestCount": 439,
            "voteCount": 451
        },
        {
            "id": "nt0728750",
            "text": "As of 2018, she is the most nominated actress with 21 Academy Award nominations.",
            "interestCount": 526,
            "voteCount": 538
        },
        {
            "id": "nt0736466",
            "text": "She was awarded the 2010 National Medal of the Arts for her services to drama.",
            "interestCount": 29,
            "voteCount": 34
        },
        {
            "id": "nt0789416",
            "text": "Recipient of the 2011 Kennedy Center Honors, along with Barbara Cook, Neil Diamond, Yo-Yo Ma and Sonny Rollins.",
            "interestCount": 39,
            "voteCount": 42
        },
        {
            "id": "nt0843182",
            "text": "She was considered for the role of Ellen Ripley in Alien (1979), which went to her good friend Sigourney Weaver.",
            "interestCount": 23,
            "voteCount": 29
        },
        {
            "id": "nt0846623",
            "text": "Is one of only four thespians to be nominated for acting honors by the Academy of Motion Picture Arts and Sciences over five decades - 1970s, 1980s, 1990s, 2000s, 2010s. Along with Laurence Olivier (1930s-1970s), Paul Newman (1950s, 1960s, 1980s, 1990s, and 2000s) and Katherine Hepburn (1930s, 1940s, 1950s, 1960s, 1980s).",
            "interestCount": 92,
            "voteCount": 100
        },
        {
            "id": "nt0881720",
            "text": "Referenced in 'Weird Al' Yankovic's song \"Your Horoscope for Today\".",
            "interestCount": 22,
            "voteCount": 28
        },
        {
            "id": "nt0896129",
            "text": "Claimed to have had a photographic memory when she was younger, which allowed her to memorize her lines after one reading.",
            "interestCount": 442,
            "voteCount": 453
        },
        {
            "id": "nt0921512",
            "text": "Spokesperson for the Center for Reproductive Rights' Draw the Line campaign. The Center for Reproductive Rights is a global legal organization dedicated to advancing women's reproductive health, self-determination and dignity as basic human rights.",
            "interestCount": 57,
            "voteCount": 63
        },
        {
            "id": "nt0929658",
            "text": "Gave birth to her first child at age 30, a son Henry Wolfe Gummer (aka Henry Gummer) on November 13, 1979. Child's father is her husband, Don Gummer.",
            "interestCount": 91,
            "voteCount": 97
        },
        {
            "id": "nt0929659",
            "text": "Gave birth to her second child at age 34, a daughter Mary Willa Gummer (aka Mamie Gummer) on August 3, 1983. Child's father is her husband, Don Gummer.",
            "interestCount": 57,
            "voteCount": 66
        },
        {
            "id": "nt0929660",
            "text": "Gave birth to her third child at age 36, a daughter Grace Jane Gummer (aka Grace Gummer) on May 9, 1986. Child's father is her husband, Don Gummer.",
            "interestCount": 40,
            "voteCount": 49
        },
        {
            "id": "nt0929661",
            "text": "Gave birth to her fourth child at age 41, a daughter Louisa Jacobson Gummer (aka Louisa Jacobson) on June 12, 1991. Child's father is her husband, Don Gummer.",
            "interestCount": 124,
            "voteCount": 129
        },
        {
            "id": "nt0988051",
            "text": "In 2013, she presented the Best Actor Oscar to Daniel Day-Lewis for Lincoln (2012). The previous year, she had received her third Oscar (second for Best Actress) for The Iron Lady (2011), and she give Lewis his third Best Actor Oscar. Both won their third Oscar for playing a Head of Government of a different nationality: Streep was an American actress playing a British Prime Minister, while Day-Lewis is a British actor playing an American President. In addition, Day-Lewis was not the only actor playing Abraham Lincoln that year. The role was played in Abraham Lincoln: Vampire Hunter (2012) by Benjamin Walker, who was married to Streep's daughter Mamie Gummer.",
            "interestCount": 201,
            "voteCount": 212
        },
        {
            "id": "nt0988052",
            "text": "Was a finalist for the role of Ellen Ripley in Alien (1979), but the role went to good friend and classmate Sigourney Weaver instead. However, Streep later got to make her own contribution to the character. Many of the special effects for Alien³ (1992) were created in England, after the cast; including Weaver; had returned home to the United States. The filmmakers needed a prosthetic cast of Ripley's head for some shots, so rather than call back Weaver, they used an available cast of Streep that had been made for a previous project and was still floating around the studio.",
            "interestCount": 106,
            "voteCount": 111
        },
        {
            "id": "nt1001250",
            "text": "Her father was of German and Swiss-German descent, and his patrilineal ancestors had originally been surnamed Streeb. For much of her life, Meryl had incorrectly believed that the family was from the Netherlands. Her mother had English, German, Irish, Scots-Irish/Northern Irish, Scottish, and remote French and Swedish, ancestry, and was descended from early settlers in Pennsylvania. One of Meryl's maternal great-grandmothers, Mary Agnes McFadden, was born in Ireland.",
            "interestCount": 40,
            "voteCount": 47
        },
        {
            "id": "nt1152110",
            "text": "She was awarded Commander of the Order of the Arts and Letters by French culture minister Jean-Jacques Aillagon in 2003.",
            "interestCount": 15,
            "voteCount": 30
        },
        {
            "id": "nt1161788",
            "text": "She was awarded a Star on the Hollywood Walk of Fame at 7018 Hollywood Boulevard in Hollywood, California on September 16, 1998.",
            "interestCount": 26,
            "voteCount": 38
        },
        {
            "id": "nt1205609",
            "text": "She has appeared in seven films that have been nominated for the Best Picture Oscar: Julia (1977), The Deer Hunter (1978), Kramer vs. Kramer (1979), Out of Africa (1985), The Hours (2002), The Post (2017), Little Women (2019) and Don't Look Up (2021). The Deer Hunter, Kramer vs. Kramer and Out of Africa won in the category.",
            "interestCount": 53,
            "voteCount": 58
        },
        {
            "id": "nt1207892",
            "text": "Is one of 6 actresses to have been pregnant at the time of winning the Academy Award; the others are Eva Marie Saint, Patricia Neal, Catherine Zeta-Jones, Rachel Weisz and Natalie Portman. Neal is the only to have not accepted her award in person as a result of her pregnancy. Streep was 5 months pregnant with her daughter Mamie Gummer when she won the Best Actress Oscar for Sophie's Choice (1982).",
            "interestCount": 115,
            "voteCount": 123
        },
        {
            "id": "nt1217496",
            "text": "Was the 82nd actress to receive an Academy Award; she won the Best Supporting Actress Oscar for Kramer vs. Kramer (1979) at The 52nd Annual Academy Awards (1980) on April 14, 1980.",
            "interestCount": 17,
            "voteCount": 36
        },
        {
            "id": "nt1222397",
            "text": "In 2013, David Letterman revealed that the director Harmony Korine had been banned from appearing on Letterman's show during the late 1990s when Letterman personally caught Korine rifling through Meryl Streep's purse in a dressing room. Streep and Korine had both been scheduled to appear on Letterman's show that night, but only Streep did.",
            "interestCount": 237,
            "voteCount": 246
        },
        {
            "id": "nt1278997",
            "text": "According to biographer Diana Maychick when companion John Cazale was too weak to read the newspapers, Streep read the paper to him imitating well-known broadcaster Warner Wolf's voice.",
            "interestCount": 97,
            "voteCount": 102
        },
        {
            "id": "nt1282756",
            "text": "She was awarded the Presidential Medal of Freedom by President Barack Obama on November 24, 2014.",
            "interestCount": 116,
            "voteCount": 123
        },
        {
            "id": "nt1287990",
            "text": "Meryl Streep sings in Silkwood (1983), Heartburn (1986), and Postcards from the Edge (1990), all of which were directed by Mike Nichols.",
            "interestCount": 59,
            "voteCount": 63
        },
        {
            "id": "nt1289740",
            "text": "Donated her entire salary for The Iron Lady (2011) to the Women's History Museum.",
            "interestCount": 327,
            "voteCount": 333
        },
        {
            "id": "nt1324643",
            "text": "Is one of 27 actresses to have received an Academy Award nomination for their performance in a musical; hers being Into the Woods (2014). The others, in chronological order, are: Bessie Love for The Broadway Melody (1929), Grace Moore for One Night of Love (1934), Jean Hagen for Singin' in the Rain (1952), Marjorie Rambeau for Torch Song (1953), Dorothy Dandridge for Carmen Jones (1954), Deborah Kerr for The King and I (1956), Rita Moreno for West Side Story (1961), Gladys Cooper for My Fair Lady (1964)), Julie Andrews for Mary Poppins (1964), The Sound of Music (1965), and Victor/Victoria (1982), Debbie Reynolds for The Unsinkable Molly Brown (1964), Peggy Wood for The Sound of Music (1965), Carol Channing for Thoroughly Modern Millie (1967), Kay Medford for Funny Girl (1968), Barbra Streisand for Funny Girl (1968), Liza Minnelli for Cabaret (1972), Ronee Blakley for Nashville (1975), Lily Tomlin for Nashville (1975), Ann-Margret for Tommy (1975), Lesley Ann Warren for Victor/Victoria (1982), Amy Irving for Yentl (1983), Nicole Kidman for Moulin Rouge! (2001), Queen Latifah for Chicago (2002), Catherine Zeta-Jones for Chicago (2002), Renée Zellweger for Chicago (2002), Jennifer Hudson for Dreamgirls (2006), Penélope Cruz for Nine (2009), Anne Hathaway for Les Misérables (2012), and Emma Stone for La La Land (2016).",
            "interestCount": 26,
            "voteCount": 37
        },
        {
            "id": "nt1327050",
            "text": "Ever since her first Oscar nomination, 66 actresses have been one of her four co-nominees in the same category, spanning an age gap of 81 years (five generations) from Katharine Hepburn to Emma Stone. Among them, 13 actresses were co-nominated twice: Cate Blanchett, Debra Winger, Helen Mirren, Jane Alexander, Jessica Lange, Judi Dench, Julianne Moore, Kate Winslet, Kathy Bates, Sandra Bullock, Emma Stone, Julianne Moore and Susan Sarandon. So far, her greatest rival, with three Oscar co-nominations, is still Glenn Close.",
            "interestCount": 41,
            "voteCount": 50
        },
        {
            "id": "nt1363494",
            "text": "Her role in Music of the Heart (1999) is the only performance for which Wes Craven directed an actor to an Oscar nomination.",
            "interestCount": 53,
            "voteCount": 56
        },
        {
            "id": "nt1368801",
            "text": "Is one of 14 actresses who won their Best Supporting Actress Oscars in a movie that also won the Best Picture Oscar (she won for Kramer vs. Kramer (1979)). The others are Hattie McDaniel for Gone with the Wind (1939), Teresa Wright for Mrs. Miniver (1942), Celeste Holm for Gentleman's Agreement (1947), Mercedes McCambridge for All the King's Men (1949), Donna Reed for From Here to Eternity (1953), Eva Marie Saint for On the Waterfront (1954), Rita Moreno for West Side Story (1961), Juliette Binoche for The English Patient (1996), Judi Dench for Shakespeare in Love (1998), Jennifer Connelly for A Beautiful Mind (2001), Catherine Zeta-Jones for Chicago (2002),Lupita Nyong'o for 12 Years a Slave (2013) and Jamie Lee Curtis for Everything Everywhere All at Once (2022).",
            "interestCount": 19,
            "voteCount": 31
        },
        {
            "id": "nt1373637",
            "text": "She won an Oscar for playing Margaret Thatcher in The Iron Lady (2011), making her one of 19 actors to win the Award for playing a real person who was still alive at the evening of the Award ceremony (as of 2017). The other sixteen actors and their respective performances are: Spencer Tracy for playing Father Edward Flanagan in Boys Town (1938), Gary Cooper for playing Alvin C. York in Sergeant York (1941), Patty Duke for playing Helen Keller in The Miracle Worker (1962), Jason Robards for playing Ben Bradlee in All the President's Men (1976), Robert De Niro for playing Jake La Motta in Raging Bull (1980), Sissy Spacek for playing Loretta Lynn in Coal Miner's Daughter (1980), Jeremy Irons for playing Claus Von Bullow in Reversal of Fortune (1990), Susan Sarandon for playing Sister Helen Prejean in Dead Man Walking (1995), Geoffrey Rush for playing David Helfgott in Shine (1996), Julia Roberts for playing Erin Brockovich in Erin Brockovich (2000), Jennifer Connelly for playing Alicia Nash in A Beautiful Mind (2001), Jim Broadbent for playing John Bayley in Iris (2001), Helen Mirren for playing Queen Elizabeth II in The Queen (2006), Sandra Bullock for playing Leigh Anne Tuohy in The Blind Side (2009), Melissa Leo for playing Alice Eklund-Ward in The Fighter (2010), Christian Bale for playing Dickie Eklund in The Fighter (2010), Eddie Redmayne for playing Stephen Hawking in The Theory of Everything (2014), and Allison Janney for playing LaVona Golden in I, Tonya (2017).",
            "interestCount": 43,
            "voteCount": 49
        },
        {
            "id": "nt1412808",
            "text": "President of the 'Official Competition' jury at the 66th Berlin International Film Festival in 2016.",
            "interestCount": 11,
            "voteCount": 16
        },
        {
            "id": "nt1478573",
            "text": "Her daughter, Grace Gummer, stars as Nora Ephron in Good Girls Revolt (2015). Streep starred in three films written by Ephron: Silkwood (1983), Heartburn (1986) and Julie & Julia (2009).",
            "interestCount": 33,
            "voteCount": 36
        },
        {
            "id": "nt1496769",
            "text": "Campaigned for Hillary Clinton in the 2016 Presidential Election.",
            "interestCount": 33,
            "voteCount": 41
        },
        {
            "id": "nt1515394",
            "text": "She played a character based on Carrie Fisher in Postcards from the Edge (1990), and then became godmother to Fisher's real-life daughter, Billie Lourd.",
            "interestCount": 106,
            "voteCount": 109
        },
        {
            "id": "nt1527084",
            "text": "She presented director Mike Nichols his AFI Lifetime Achievement Award in 2010.",
            "interestCount": 13,
            "voteCount": 16
        },
        {
            "id": "nt1553044",
            "text": "Is one of 19 actresses to have received a Best Actress Oscar nomination for a performance where they acted out a labor and/or birth; hers being for A Cry in the Dark (1988). The others in chronological order are Luise Rainer for The Good Earth (1937), Jane Wyman for Johnny Belinda (1948), Eleanor Parker for Caged (1950), Elizabeth Taylor for Raintree County (1957), Leslie Caron for The L-Shaped Room (1962), Shirley MacLaine for Irma la Douce (1963), Vanessa Redgrave for Isadora (1968), Geneviève Bujold for Anne of the Thousand Days (1969), Marsha Mason for Cinderella Liberty (1973), Ann-Margret for Tommy (1975), Ellen Burstyn for Same Time, Next Year (1978), Jessica Lange for Sweet Dreams (1985), Samantha Morton for In America (2002), Elliot Page for Juno (2007), Gabourey Sidibe for Precious (2009), Ruth Negga for Loving (2016), Yalitza Aparicio for Roma (2018) and Vanessa Kirby for Pieces of a Woman (2020).",
            "interestCount": 7,
            "voteCount": 15
        },
        {
            "id": "nt1581725",
            "text": "She has worked with 11 directors who have won a Best Director Oscar: Fred Zinnemann, Michael Cimino, Woody Allen, Robert Benton, Mike Nichols, Sydney Pollack, Robert Zemeckis, Jonathan Demme, Robert Redford, Steven Spielberg, and Steven Soderbergh.",
            "interestCount": 14,
            "voteCount": 17
        },
        {
            "id": "nt1581726",
            "text": "She is one of only 4 actors to have been Oscar nominated for a performance in a film from Walt Disney Pictures, for Into the Woods (2014). The only other actors to have achieved this feat are Julie Andrews, Richard Farnsworth, and Johnny Depp.",
            "interestCount": 48,
            "voteCount": 50
        },
        {
            "id": "nt1611993",
            "text": "Friends with Diane Keaton and Viola Davis.",
            "interestCount": 46,
            "voteCount": 50
        },
        {
            "id": "nt1648206",
            "text": "Gives an Oscar nominated performance each time she appears in a film which won the Academy Award for Best Picture. She was nominated for Best Supporting Actress for The Deer Hunter (1978), won Best Supporting Actress for Kramer vs. Kramer (1979) and was nominated for Best Actress for Out of Africa (1985).",
            "interestCount": 8,
            "voteCount": 10
        },
        {
            "id": "nt1688268",
            "text": "Born on the same date as Lindsay Wagner, of The Bionic Woman (1976) fame.",
            "interestCount": 15,
            "voteCount": 22
        },
        {
            "id": "nt1715609",
            "text": "Returned to work six months after giving birth to her daughter Louisa to begin filming Death Becomes Her (1992).",
            "interestCount": 18,
            "voteCount": 21
        },
        {
            "id": "nt1715610",
            "text": "Returned to work nine months after giving birth to her daughter Grace Gummer to begin filming Ironweed (1987).",
            "interestCount": 7,
            "voteCount": 14
        },
        {
            "id": "nt1715611",
            "text": "Was two months pregnant with her daughter Grace Gummer when she completed filming on Heartburn (1986).",
            "interestCount": 9,
            "voteCount": 19
        },
        {
            "id": "nt1715612",
            "text": "Returned to work seven months after giving birth to her daughter Mamie Gummer to begin filming Falling in Love (1984).",
            "interestCount": 8,
            "voteCount": 15
        },
        {
            "id": "nt1715613",
            "text": "Returned to work six months after giving birth to her son Henry Gummer to begin filming The French Lieutenant's Woman (1981).",
            "interestCount": 12,
            "voteCount": 16
        },
        {
            "id": "nt1715614",
            "text": "Was not pregnant with her son Henry Gummer despite many reports to the contrary whilst filming Kramer vs. Kramer (1979) as production on the film ended in December 1978 and Streep did not fall pregnant until February 1979.",
            "interestCount": 18,
            "voteCount": 22
        },
        {
            "id": "nt1769917",
            "text": "She has appeared in three films that have been selected for the National Film Registry by the Library of Congress as being \"culturally, historically or aesthetically\" significant: The Deer Hunter (1978), Manhattan (1979) and The Hours (2002).",
            "interestCount": 16,
            "voteCount": 18
        },
        {
            "id": "nt1817196",
            "text": "She and American Senator Elizabeth Warren were born on the same day (June 22, 1949).",
            "interestCount": 19,
            "voteCount": 27
        },
        {
            "id": "nt1856819",
            "text": "As of 2019, Meryl Streep holds the record for most Academy Award nominations for Best Actress (17 nominations); as well as, the records for most Golden Globe nominations for Best Actress - Drama (14), Best Actress - Comedy or Musical (10), and Best Supporting Actress (5, tied with Lee Grant and Maureen Stapleton ) in feature films.",
            "interestCount": 8,
            "voteCount": 11
        },
        {
            "id": "nt1918591",
            "text": "She rewrote her court room scene in Kramer vs. Kramer (1979).",
            "interestCount": 60,
            "voteCount": 62
        },
        {
            "id": "nt1925635",
            "text": "Has acted out giving birth in three of her movies; Heartburn (1986), A Cry in the Dark (1988) and The House of the Spirits (1993).",
            "interestCount": 11,
            "voteCount": 14
        },
        {
            "id": "nt1974760",
            "text": "Is a fan of Olivia Colman. Colman played her daughter Carol Thatcher in The Iron Lady (2011) and Streep is a fan of Colman's performance in Paddy Considine's directorial debut Tyrannosaur (2011).",
            "interestCount": 44,
            "voteCount": 46
        },
        {
            "id": "nt1998013",
            "text": "Despite being Oscar-nominated and winning Golden Globe and BAFTA trophies for her performance in The French Lieutenant's Woman (1981), Meryl has said that it is her least favorite personal performance of all her films, partly because the narrative structure felt artificial. Thus, as a young American actress playing an Englishwoman, she never felt her character really rang true in that context.",
            "interestCount": 23,
            "voteCount": 25
        },
        {
            "id": "nt2036530",
            "text": "Has six grandchildren; a grandson Peter (b. February 2019) and a granddaughter Mary (b. 2021), via daughter Mamie Gummer, another granddaughter, Ida June Gummer (b. July 18, 2020) and another grandson, Quinn William Gummer (b. May 6, 2022), via son Henry Gummer and two granddaughters (the first one, Ruthie, b. 2023 and the second in 2025 respectively) via daughter Grace Gummer.",
            "interestCount": 34,
            "voteCount": 34
        },
        {
            "id": "nt2041440",
            "text": "Born at 8:05 AM (EDT).",
            "interestCount": 7,
            "voteCount": 15
        },
        {
            "id": "nt2419735",
            "text": "Speaks fluent Italian.",
            "interestCount": 4,
            "voteCount": 4
        },
        {
            "id": "nt2472967",
            "text": "Meryl is a Master Number 33 in numerology. The rarest number ( 1% of the world) and people with this number are the Master Teachers of our planet.",
            "interestCount": 1,
            "voteCount": 5
        }
    ],
    "totalCount": 138
}